{
	"name": "CEOP",
	"properties": {
		"activities": [
			{
				"name": "Copy data1",
				"type": "Copy",
				"dependsOn": [
					{
						"activity": "Filtro",
						"dependencyConditions": [
							"Succeeded"
						]
					}
				],
				"policy": {
					"timeout": "7.00:00:00",
					"retry": 0,
					"retryIntervalInSeconds": 30,
					"secureOutput": false,
					"secureInput": false
				},
				"userProperties": [],
				"typeProperties": {
					"source": {
						"type": "ExcelSource",
						"additionalColumns": [
							{
								"name": "Ultima_Coluna",
								"value": {
									"value": "VLR_TESTE",
									"type": "Expression"
								}
							}
						],
						"storeSettings": {
							"type": "AzureBlobFSReadSettings",
							"recursive": true,
							"enablePartitionDiscovery": false
						}
					},
					"sink": {
						"type": "AzureSqlSink",
						"writeBehavior": "insert",
						"sqlWriterUseTableLock": false,
						"tableOption": "autoCreate",
						"disableMetricsCollection": false
					},
					"enableStaging": false,
					"translator": {
						"type": "TabularTranslator",
						"typeConversion": true,
						"typeConversionSettings": {
							"allowDataTruncation": true,
							"treatBooleanAsNumber": false
						}
					}
				},
				"inputs": [
					{
						"referenceName": "CEOP_DS_EXCEL",
						"type": "DatasetReference"
					}
				],
				"outputs": [
					{
						"referenceName": "AZ_SQL_STG",
						"type": "DatasetReference",
						"parameters": {
							"SCHEMA": "stg",
							"TABELA": "ceop"
						}
					}
				]
			},
			{
				"name": "Lista arquivos",
				"type": "GetMetadata",
				"dependsOn": [],
				"policy": {
					"timeout": "0.02:00:00",
					"retry": 0,
					"retryIntervalInSeconds": 30,
					"secureOutput": false,
					"secureInput": false
				},
				"userProperties": [],
				"typeProperties": {
					"dataset": {
						"referenceName": "DS_HMAISDATADRIVEN",
						"type": "DatasetReference",
						"parameters": {
							"FileSystem": "ceop"
						}
					},
					"fieldList": [
						"childItems",
						"itemType",
						"itemName",
						"lastModified"
					],
					"storeSettings": {
						"type": "AzureBlobFSReadSettings",
						"recursive": true,
						"enablePartitionDiscovery": false
					},
					"formatSettings": {
						"type": "BinaryReadSettings"
					}
				}
			},
			{
				"name": "Filtro",
				"type": "Filter",
				"dependsOn": [
					{
						"activity": "Lista arquivos",
						"dependencyConditions": [
							"Succeeded"
						]
					}
				],
				"userProperties": [],
				"typeProperties": {
					"items": {
						"value": "@activity('Lista arquivos').output.childItems",
						"type": "Expression"
					},
					"condition": {
						"value": "@endsWith(item().name, 'xlsx')",
						"type": "Expression"
					}
				}
			}
		],
		"folder": {
			"name": "Data Warehouse/P&P"
		},
		"annotations": []
	}
}