{
	"name": "Maqplan",
	"properties": {
		"activities": [
			{
				"name": "Maqplan_Vendas",
				"type": "DatabricksNotebook",
				"dependsOn": [],
				"policy": {
					"timeout": "0.12:00:00",
					"retry": 0,
					"retryIntervalInSeconds": 30,
					"secureOutput": false,
					"secureInput": false
				},
				"userProperties": [],
				"typeProperties": {
					"notebookPath": "/Maqplan/VendaPorItem_Carga"
				},
				"linkedServiceName": {
					"referenceName": "AzureDatabricks",
					"type": "LinkedServiceReference"
				}
			}
		],
		"folder": {
			"name": "Data Warehouse"
		},
		"annotations": []
	}
}