{
	"name": "Daily 23 55",
	"properties": {
		"annotations": [],
		"runtimeState": "Started",
		"pipelines": [
			{
				"pipelineReference": {
					"referenceName": "Kill_Sessions_Sql",
					"type": "PipelineReference"
				}
			}
		],
		"type": "ScheduleTrigger",
		"typeProperties": {
			"recurrence": {
				"frequency": "Day",
				"interval": 1,
				"startTime": "2022-11-07T22:50:00",
				"timeZone": "E. South America Standard Time",
				"schedule": {
					"minutes": [
						55
					],
					"hours": [
						23
					]
				}
			}
		}
	}
}